nbase/__init__.py
nbase/config.py
nbase/helpers.py
Nbase-0.1.dist-info/LICENSE
Nbase-0.1.dist-info/METADATA
Nbase-0.1.dist-info/WHEEL
Nbase-0.1.dist-info/top_level.txt
Nbase-0.1.dist-info/RECORD
