Metadata-Version: 2.1
Name: Nbase
Version: 0.1
Summary: A simple toolkit for Nio UDP team.
Home-page: UNKNOWN
Author: Ding Weihua
Author-email: weihua.ding@nio.com
License: UNKNOWN
Platform: UNKNOWN
Classifier: Programming Language :: Python :: 3
Classifier: License :: OSI Approved :: MIT License
Classifier: Operating System :: OS Independent
